setup.py
jklslsls/__init__.py
jklslsls.egg-info/PKG-INFO
jklslsls.egg-info/SOURCES.txt
jklslsls.egg-info/dependency_links.txt
jklslsls.egg-info/top_level.txt